{
  "$schema": "https://unpkg.com/knip@latest/schema.json",
  "entry": [
    "app/**/page.tsx",
    "app/**/layout.tsx",
    "app/**/route.ts",
    "app/**/loading.tsx",
    "app/**/error.tsx",
    "app/**/not-found.tsx",
    "app/**/default.tsx",
    "middleware.ts",
    "proxy.ts",
    "next.config.mjs",
    "playwright.config.ts",
    "scripts/cron-runner.ts",
    "scripts/**/*.ts",
    "scripts/**/*.js",
    "scripts/**/*.cjs",
    "prisma/seed.ts",
    "prisma/clean-db.ts",
    "prisma-scripts/**/*.ts",
    "supabase/functions/**/index.ts",
    "tests/**/*.spec.ts",
    "tests/auth.setup.ts",
    "public/register-sw.js",
    "public/sw.js",
    "components/layout/provider-groups.tsx",
    "components/layout/client-layout.tsx",
    "hooks/use-feeding.ts",
    "lib/recharts-dynamic.tsx",
    "lib/context/**/*.tsx"
  ],
  "project": [
    "app/**/*.{ts,tsx}",
    "components/**/*.{ts,tsx}",
    "hooks/**/*.{ts,tsx}",
    "lib/**/*.{ts,tsx}",
    "utils/**/*.{ts,tsx}",
    "scripts/**/*.{ts,tsx,js,cjs}",
    "tests/**/*.{ts,tsx}",
    "prisma/**/*.ts",
    "prisma-scripts/**/*.ts"
  ],
  "ignore": [
    "public/**",
    ".agents/**",
    ".cursor/**",
    "dogfood-output/**",
    "components/ui/**",
    "index.ts",
    "jest.setup.js",
    "src/**",
    "types/**",
    "components/add-event-dialog.tsx",
    "components/animated-icon.tsx",
    "components/animated-list.tsx",
    "components/error-boundary.tsx",
    "components/image-upload.tsx",
    "components/no-data-message.tsx",
    "components/timeline-event.tsx",
    "hooks/use-mobile.tsx",
    "lib/constants.ts",
    "components/auth/auth-status.tsx",
    "components/cats/WeightTrendChart.tsx",
    "components/feeding/feeding-drawer.tsx",
    "components/feeding/feeding-form.tsx",
    "components/feeding/feeding-progress.tsx",
    "components/feeding/feeding-schedule.tsx",
    "components/feeding/types.ts",
    "components/feeding/upcoming-feedings.tsx",
    "components/household/HouseholdMembers.tsx",
    "components/household/HouseholdPets.tsx",
    "components/notifications/notification-list.tsx",
    "components/providers/toaster.tsx",
    "components/skeletons/data-table-skeleton.tsx",
    "components/weight/lazy-chart-wrapper.tsx",
    "lib/context/ContextBridge.tsx",
    "lib/context/StateSync.tsx",
    "lib/dto/**",
    "lib/hooks/use-animation.ts",
    "lib/hooks/use-local-storage.ts",
    "lib/hooks/use-notification-sync.ts",
    "lib/hooks/useDataFetching.ts",
    "lib/middleware/rate-limit.ts",
    "lib/monitoring/error-monitor.ts",
    "lib/monitoring/feeding-notifications.ts",
    "lib/prisma/safe-access.ts",
    "lib/services/feeding-service.ts",
    "lib/services/notification-service.ts",
    "lib/services/statistics-service.ts",
    "lib/utils/EventSystem.ts",
    "lib/utils/Memoization.ts",
    "lib/utils/PerformanceMonitor.ts",
    "lib/utils/StateSelectors.ts",
    "lib/utils/StorageAnalytics.ts",
    "lib/utils/StorageService.ts",
    "lib/utils/api-utils.ts",
    "lib/utils/cache.ts",
    "lib/utils/data-loader.ts",
    "lib/utils/security-headers.ts",
    "lib/utils/storage.ts",
    "lib/utils/validation.ts",
    "lib/validations/**",
    "app/cats/[id]/settings-client-page.tsx",
    "components/ui/chart-impl.tsx",
    "app/statistics/statistics-chart-components.tsx",
    "app/components/dashboard/dashboard-feedings-chart.tsx",
    "components/weight/current-status-card.tsx",
    "components/weight/recent-history-list.tsx",
  ],
  "ignoreDependencies": [
    "ts-node",
    "form-data",
    "swagger-ui-dist"
  ],
  "ignoreExportsUsedInFile": true,
  "ignoreIssues": {
    "utils/supabase/middleware.ts": ["exports"],
    "lib/middleware/mobile-auth.ts": ["exports"],
    "lib/context/HouseholdContext.tsx": ["exports"],
    "lib/prisma.ts": ["exports"],
    "lib/auth.ts": ["exports", "types"],
    "lib/services/notificationService.ts": ["exports", "types"],
    "lib/middleware/deprecated-warning.ts": ["exports"],
    "lib/utils/error-sanitizer.ts": ["exports"],
    "lib/image-errors.ts": ["exports"],
    "lib/utils/error-handler.ts": ["exports"],
    "lib/context/ErrorContext.tsx": ["exports"],
    "lib/utils/dateUtils.ts": ["exports"],
    "lib/mailersend.ts": ["exports"],
    "lib/context/FeedingContext.tsx": ["exports"],
    "lib/context/CatsContext.tsx": ["exports"],
    "components/onboarding-wrapper.tsx": ["exports"],
    "lib/services/apiService.ts": ["exports"],
    "lib/services/api-feeding-service.ts": ["exports"],
    "lib/data.ts": ["exports"],
    "lib/utils/feedingUtils.ts": ["exports"],
    "lib/selectors/statisticsSelectors.ts": ["exports", "types"],
    "lib/utils/date.ts": ["exports", "types"],
    "lib/context/WeightContext.tsx": ["exports"],
    "utils/supabase/storage.ts": ["exports"],
    "lib/repositories/cat-repository.ts": ["exports"],
    "lib/repositories/household-repository.ts": ["exports"],
    "lib/repositories/schedule-repository.ts": ["exports"],
    "lib/types.ts": ["types"],
    "lib/types/common.ts": ["types"],
    "lib/utils/api-error-handling.ts": ["types"],
    "lib/types/notification.ts": ["types"],
    "types/monitoring.ts": ["types"],
    "components/layout/authenticated-layout.tsx": ["types"]
  }
}
